goifer/__init__.py
goifer/client.py
goifer/config.yml
goifer/errors.py
goifer/response.py
goifer-0.0.5.dist-info/LICENSE.md
goifer-0.0.5.dist-info/WHEEL
goifer-0.0.5.dist-info/METADATA
goifer-0.0.5.dist-info/RECORD
