Metadata-Version: 2.1
Name: goifer
Version: 0.0.5
Summary: Client for Gever of the canton of Zurich
Author-email: Stefan Oderbolz <odi@metaodi.ch>
Requires-Python: >=3.7
Classifier: License :: OSI Approved :: MIT License
Requires-Dist: requests
Requires-Dist: muzzle
Requires-Dist: pyyaml
Requires-Dist: flatten-dict
Requires-Dist: black ; extra == "dev"
Requires-Dist: flit ; extra == "dev"
Requires-Dist: pandas ; extra == "dev"
Requires-Dist: termcolor ; extra == "dev"
Requires-Dist: flake8 ; extra == "test"
Requires-Dist: mock ; extra == "test"
Requires-Dist: responses ; extra == "test"
Requires-Dist: pytest ; extra == "test"
Requires-Dist: pytest-cov ; extra == "test"
Project-URL: Home, https://github.com/metaodi/goifer
Provides-Extra: dev
Provides-Extra: test
